github_dependents_info/__init__.py
github_dependents_info/__main__.py
github_dependents_info/gh_dependents_info.py
github_dependents_info-3.0.0.dist-info/METADATA
github_dependents_info-3.0.0.dist-info/WHEEL
github_dependents_info-3.0.0.dist-info/entry_points.txt
github_dependents_info-3.0.0.dist-info/licenses/LICENSE
github_dependents_info-3.0.0.dist-info/RECORD
