Metadata-Version: 2.4
Name: github-dependents-info
Version: 3.0.0
Summary: Collect information about dependencies between a github repo and other repositories. Results available in JSON, markdown and badges.
License-Expression: MIT
License-File: LICENSE
Keywords: github,dependent,used-by,repository,stats,dependencies,using
Author: nvuillam
Author-email: nicolas.vuillamy@gmail.com
Requires-Python: >=3.10,<4.0
Classifier: Development Status :: 3 - Alpha
Classifier: Intended Audience :: Developers
Classifier: Operating System :: OS Independent
Classifier: Topic :: Software Development :: Libraries :: Python Modules
Classifier: Programming Language :: Python :: 3
Classifier: Programming Language :: Python :: 3.9
Requires-Dist: beautifulsoup4 (==4.14.3)
Requires-Dist: click (>=8.3.1,<8.4)
Requires-Dist: httpx (>=0.28.1,<0.29.0)
Requires-Dist: idna (>=3.11)
Requires-Dist: litellm (>=1.60.0,<2.0)
Requires-Dist: pandas (>=2.3.3,<3.0)
Requires-Dist: rich (>=14.2,<14.3)
Requires-Dist: typer-slim (>=0.19,<0.20)
Requires-Dist: typer[standard] (>=0.19,<0.20)
Project-URL: Homepage, https://github.com/nvuillam/github-dependents-info
Project-URL: Repository, https://github.com/nvuillam/github-dependents-info
